{
    "info": {
        "added": 1647710771.97796, 
        "started": 1647719956.563371, 
        "duration": 731, 
        "ended": 1647720687.838277, 
        "owner": null, 
        "score": 0.0, 
        "id": 2869714, 
        "category": "file", 
        "git": {
            "head": "e8f6317b4b3ef806085a1e99e64c6ff01f26948f", 
            "fetch_head": "e8f6317b4b3ef806085a1e99e64c6ff01f26948f"
        }, 
        "monitor": "2deb9ccd75d5a7a3fe05b2625b03a8639d6ee36b", 
        "package": "", 
        "route": "internet", 
        "custom": null, 
        "machine": {
            "status": "stopped", 
            "name": "Ubuntu1904x647", 
            "label": "Ubuntu1904x647", 
            "platform": "linux", 
            "manager": "VirtualBox", 
            "started_on": "2022-03-19 19:59:17", 
            "shutdown_on": "2022-03-19 20:11:27"
        }, 
        "platform": null, 
        "version": "2.0.7", 
        "options": "procmemdump=yes,route=internet"
    }, 
    "signatures": [], 
    "target": {
        "category": "file", 
        "file": {
            "mimetype": "application/x-chrome-extension", 
            "yara": [], 
            "sha1": "d3c35cfb9c9054f1ca47da99a405a6c07c0d4a07", 
            "name": "extension_0_9_2_0 (1).crx", 
            "type": "Google Chrome extension, version 3", 
            "sha256": "4543e1290b51e98a1fb0bd4c110ae19e86b13e76edcdd34dfe0afdbbe0487303", 
            "urls": [], 
            "crc32": "4647FFE4", 
            "path": "/srv/cuckoo/cwd/storage/binaries/4543e1290b51e98a1fb0bd4c110ae19e86b13e76edcdd34dfe0afdbbe0487303", 
            "ssdeep": "24576:HuQYZ12AODMYWGZNaBBjAFXRHAUCUmGAP6mWF+lGp5K12IqDM5mZlBkLAEbtOz2r:HhmQgl1jUVnIG645KYg5qUGb1c1Q/hjw", 
            "size": 1784662, 
            "sha512": "8f2d4753e98ffb3696183830a008b18b95f9bbe7a45d6a6eefe9385e143aaf6b8198a191ca70a2b9b856ead748005b5966ea67041066bf42bfa1e64df3ec8f5a", 
            "md5": "f63e85ebfacde32101b44f6c02972764"
        }, 
        "custom": null
    }, 
    "irma": {
        "status": 0, 
        "probes_finished": 16, 
        "scan_id": "2a612ded-0766-4305-911e-c7bb1977be7e", 
        "parent_file_sha256": null, 
        "probes_total": 16, 
        "scan_date": 1647713489, 
        "name": "4543e1290b51e98a1fb0bd4c110ae19e86b13e76edcdd34dfe0afdbbe0487303", 
        "other_results": [], 
        "submitter": "cli", 
        "file_infos": {
            "mimetype": "Google Chrome extension, version 3", 
            "sha1": "d3c35cfb9c9054f1ca47da99a405a6c07c0d4a07", 
            "tags": [], 
            "timestamp_first_scan": 1647386728.4, 
            "timestamp_last_scan": 1647713497.9, 
            "sha256": "4543e1290b51e98a1fb0bd4c110ae19e86b13e76edcdd34dfe0afdbbe0487303", 
            "md5": "f63e85ebfacde32101b44f6c02972764", 
            "size": 1784662
        }, 
        "probe_results": {
            "antivirus": {
                "Avast Core Security (Linux)": {
                    "status": 0, 
                    "duration": 0.08, 
                    "version": "3.0.3", 
                    "results": null, 
                    "virus_database_version": "unavailable"
                }, 
                "F-Secure Antivirus (Linux)": {
                    "status": 0, 
                    "duration": 0.97, 
                    "version": "11.10", 
                    "results": null, 
                    "virus_database_version": "2022-02-04_03"
                }, 
                "Windows Defender (Windows)": {
                    "status": 0, 
                    "duration": 0.55, 
                    "version": "1.1.18900.3", 
                    "results": null, 
                    "virus_database_version": "1.359.1348.0"
                }, 
                "Comodo Antivirus (Linux)": {
                    "status": 0, 
                    "duration": 2.11, 
                    "version": "1.1.268025.1", 
                    "results": null, 
                    "virus_database_version": "2021-12-31"
                }, 
                "Kaspersky Antivirus (Win)": {
                    "status": 0, 
                    "duration": 3.7, 
                    "version": "21.3", 
                    "results": null, 
                    "virus_database_version": "2022-03-11 01:06:00 (full)"
                }, 
                "ESET NOD32 Antivirus (Linux)": {
                    "status": 0, 
                    "duration": 4.84, 
                    "version": "4.0.96", 
                    "results": null, 
                    "virus_database_version": "61ad92b8-1e6f6 (2022-02-04)"
                }, 
                "GData (Windows)": {
                    "status": 0, 
                    "duration": 0.55, 
                    "version": "5.5.20197.1358", 
                    "results": null, 
                    "virus_database_version": "unavailable"
                }, 
                "Forticlient (Linux)": {
                    "status": 0, 
                    "duration": 3.12, 
                    "version": "unavailable", 
                    "results": null, 
                    "virus_database_version": "unavailable"
                }, 
                "Avira (Windows)": {
                    "status": 0, 
                    "duration": 4.11, 
                    "version": "8.3.64.66", 
                    "results": null, 
                    "virus_database_version": "8.19.1.122"
                }, 
                "eScan Antivirus (Linux)": {
                    "status": 0, 
                    "duration": 4.23, 
                    "version": "7.0.21", 
                    "results": null, 
                    "virus_database_version": "7.91093 (04/02/2022)"
                }, 
                "McAfee CLI scanner (Linux)": {
                    "status": 0, 
                    "duration": 4.46, 
                    "version": "6.0.6.653", 
                    "results": null, 
                    "virus_database_version": "10247"
                }, 
                "Sophos Anti-Virus (Linux)": {
                    "status": 0, 
                    "duration": 6.19, 
                    "version": "5.85.0", 
                    "results": null, 
                    "virus_database_version": "5.90 (01 February 2022)"
                }, 
                "DrWeb Antivirus (Linux)": {
                    "status": 0, 
                    "duration": 0.74, 
                    "version": "11.1.11.2110182032", 
                    "results": null, 
                    "virus_database_version": "unavailable"
                }, 
                "ClamAV (Linux)": {
                    "status": 0, 
                    "duration": 0.19, 
                    "version": "0.103.5", 
                    "results": null, 
                    "virus_database_version": "26474"
                }, 
                "Bitdefender Antivirus (Linux)": {
                    "status": 0, 
                    "duration": 6.44, 
                    "version": "7.90123", 
                    "results": null, 
                    "virus_database_version": null
                }, 
                "Emsisoft Commandline Scanner (Windows)": {
                    "status": 0, 
                    "duration": 1.0, 
                    "version": "2021.10.0.11201", 
                    "results": null, 
                    "virus_database_version": "unavailable"
                }
            }
        }, 
        "path": "", 
        "result_id": "ddd1dc0a-26a5-4574-a860-581ef1da53bc", 
        "file_sha256": "4543e1290b51e98a1fb0bd4c110ae19e86b13e76edcdd34dfe0afdbbe0487303"
    }, 
    "suricata": {
        "tls": [], 
        "files": [], 
        "alerts": [], 
        "http": []
    }, 
    "virustotal": {
        "summary": {
            "error": "resource has not been scanned yet"
        }
    }, 
    "network": {
        "tls": [], 
        "udp": [], 
        "dns_servers": [], 
        "http": [], 
        "icmp": [], 
        "smtp": [], 
        "tcp": [], 
        "smtp_ex": [], 
        "geoinfo": {}, 
        "mitm": [], 
        "hosts": [], 
        "pcap_sha256": "704e5e5b3234433c01fcfd1b20a306e77e985038120492dc53965c3edd38a4ea", 
        "dns": [], 
        "http_ex": [], 
        "domains": [], 
        "dead_hosts": [], 
        "irc": [], 
        "https_ex": []
    }, 
    "resubmit": {
        "resubmit_ids": []
    }, 
    "snort": {
        "alerts": []
    }, 
    "debug": {
        "action": [], 
        "dbgview": [], 
        "errors": [], 
        "log": [
            "2022-03-19 17:26:11,007 [root] DEBUG: Starting analyzer from: /tmp/tmpoJv7vi\n", 
            "2022-03-19 17:26:11,008 [root] DEBUG: Storing results at: /tmp/qEPjffvK\n", 
            "2022-03-19 17:26:11,008 [lib.core.packages] INFO: _guess_package_name failed\n", 
            "2022-03-19 17:26:11,009 [lib.core.packages] INFO: Google Chrome extension, version 3\n", 
            "2022-03-19 17:26:11,009 [lib.core.packages] INFO: extension_0_9_2_0 (1).crx\n", 
            "2022-03-19 17:26:13,820 [modules.auxiliary.filecollector] INFO: FileCollector started v0.08\n", 
            "2022-03-19 17:26:13,822 [modules.auxiliary.human] INFO: Human started v0.02\n", 
            "2022-03-19 17:26:13,825 [modules.auxiliary.screenshots] INFO: Screenshots started v0.03\n", 
            "2022-03-19 17:26:26,363 [lib.core.packages] INFO: Process startup took 12.53 seconds\n", 
            "2022-03-19 17:26:26,370 [root] INFO: Added new process to list with pid: 2073\n", 
            "2022-03-19 17:26:41,396 [root] INFO: Process with pid 2073 has terminated\n", 
            "2022-03-19 17:26:41,397 [root] INFO: Process list is empty, terminating analysis.\n", 
            "2022-03-19 17:26:44,400 [lib.core.packages] INFO: Package requested stop\n", 
            "2022-03-19 17:26:44,401 [lib.core.packages] WARNING: Exception uploading log: [Errno 3] No such process\n", 
            "2022-03-19 17:30:05,982 [root] INFO: Terminating remaining processes before shutdown.\n", 
            "2022-03-19 17:30:05,982 [root] INFO: Analysis completed.\n"
        ], 
        "cuckoo": [
            "2022-03-19 19:59:17,149 [cuckoo.core.scheduler] INFO: Task #2869714: acquired machine Ubuntu1904x647 (label=Ubuntu1904x647)\n", 
            "2022-03-19 19:59:17,149 [cuckoo.core.resultserver] DEBUG: Now tracking machine 192.168.168.107 for task #2869714\n", 
            "2022-03-19 19:59:17,545 [cuckoo.auxiliary.sniffer] INFO: Started sniffer with PID 3942720 (interface=vboxnet0, host=192.168.168.107)\n", 
            "2022-03-19 19:59:17,728 [cuckoo.machinery.virtualbox] DEBUG: Starting vm Ubuntu1904x647\n", 
            "2022-03-19 19:59:18,412 [cuckoo.machinery.virtualbox] DEBUG: Restoring virtual machine Ubuntu1904x647 to Snapshot\n", 
            "2022-03-19 20:03:40,911 [cuckoo.core.guest] INFO: Starting analysis #2869714 on guest (id=Ubuntu1904x647, ip=192.168.168.107)\n", 
            "2022-03-19 20:03:41,921 [cuckoo.core.guest] DEBUG: Ubuntu1904x647: not ready yet\n", 
            "2022-03-19 20:03:46,940 [cuckoo.core.guest] INFO: Guest is running Cuckoo Agent 0.10 (id=Ubuntu1904x647, ip=192.168.168.107)\n", 
            "2022-03-19 20:03:46,965 [cuckoo.core.guest] DEBUG: Uploading analyzer to guest (id=Ubuntu1904x647, ip=192.168.168.107, monitor=latest, size=72028)\n", 
            "2022-03-19 20:03:47,195 [cuckoo.core.resultserver] DEBUG: Task #2869714: live log analysis.log initialized.\n", 
            "2022-03-19 20:03:53,633 [cuckoo.core.resultserver] DEBUG: Task #2869714: File upload for 'shots/0001.jpg'\n", 
            "2022-03-19 20:03:53,813 [cuckoo.core.resultserver] DEBUG: Task #2869714 uploaded file length: 171585\n", 
            "2022-03-19 20:04:02,347 [cuckoo.core.guest] DEBUG: Ubuntu1904x647: analysis #2869714 still processing\n", 
            "2022-03-19 20:04:17,414 [cuckoo.core.guest] DEBUG: Ubuntu1904x647: analysis #2869714 still processing\n", 
            "2022-03-19 20:04:20,607 [cuckoo.core.resultserver] DEBUG: Task #2869714: File upload for 'logs/all.stap'\n", 
            "2022-03-19 20:04:20,611 [cuckoo.core.resultserver] DEBUG: Task #2869714 uploaded file length: 0\n", 
            "2022-03-19 20:04:32,580 [cuckoo.core.guest] DEBUG: Ubuntu1904x647: analysis #2869714 still processing\n", 
            "2022-03-19 20:04:47,731 [cuckoo.core.guest] DEBUG: Ubuntu1904x647: analysis #2869714 still processing\n", 
            "2022-03-19 20:05:02,812 [cuckoo.core.guest] DEBUG: Ubuntu1904x647: analysis #2869714 still processing\n", 
            "2022-03-19 20:05:18,098 [cuckoo.core.guest] DEBUG: Ubuntu1904x647: analysis #2869714 still processing\n", 
            "2022-03-19 20:05:33,206 [cuckoo.core.guest] DEBUG: Ubuntu1904x647: analysis #2869714 still processing\n", 
            "2022-03-19 20:05:48,315 [cuckoo.core.guest] DEBUG: Ubuntu1904x647: analysis #2869714 still processing\n", 
            "2022-03-19 20:06:03,394 [cuckoo.core.guest] DEBUG: Ubuntu1904x647: analysis #2869714 still processing\n", 
            "2022-03-19 20:06:18,526 [cuckoo.core.guest] DEBUG: Ubuntu1904x647: analysis #2869714 still processing\n", 
            "2022-03-19 20:06:33,587 [cuckoo.core.guest] DEBUG: Ubuntu1904x647: analysis #2869714 still processing\n", 
            "2022-03-19 20:06:48,778 [cuckoo.core.guest] INFO: Ubuntu1904x647: end of analysis reached!\n", 
            "2022-03-19 20:06:48,786 [cuckoo.core.plugins] DEBUG: Stopped auxiliary module: Redsocks\n", 
            "2022-03-19 20:06:48,877 [cuckoo.core.plugins] DEBUG: Stopped auxiliary module: Sniffer\n", 
            "2022-03-19 20:07:03,746 [cuckoo.machinery.virtualbox] INFO: Successfully generated memory dump for virtual machine with label Ubuntu1904x647 to path /srv/cuckoo/cwd/storage/analyses/2869714/memory.dmp\n", 
            "2022-03-19 20:07:03,747 [cuckoo.machinery.virtualbox] DEBUG: Stopping vm Ubuntu1904x647\n", 
            "2022-03-19 20:11:27,359 [cuckoo.core.resultserver] DEBUG: Stopped tracking machine 192.168.168.107 for task #2869714\n", 
            "2022-03-19 20:11:27,506 [cuckoo.core.scheduler] DEBUG: Released database task #2869714\n", 
            "2022-03-19 20:11:27,700 [cuckoo.core.scheduler] INFO: Task #2869714: analysis procedure completed\n"
        ]
    }, 
    "strings": [
        "?5AC|'", 
        "`,-/MD", 
        "update.html", 
        "images/", 
        "style/", 
        "Fika-v0.9.2.zip", 
        "mdD~wN", 
        "lacg\"fJb", 
        "k;3;FV:{[", 
        "uX!iy>x", 
        "/7#WBE", 
        "&Uw8lM", 
        "K9=8Y`", 
        "XUV-K[L", 
        "~$p$e\"", 
        "JtaE;C", 
        "KrD?BF", 
        "j(}6f%z", 
        "#SkV52", 
        "x~Q)m77Rd", 
        "!L|oos", 
        "*7@&l$", 
        "Tbb.lEE", 
        "(zzTKS;rL", 
        "-D^_1ng", 
        "~@NsIMdMCB\\{!Ojypa:ij(", 
        "\u001flZci`d9", 
        "9a:Yn?h4", 
        ";ov~y<@", 
        " lhwy;M", 
        "*t`9~D(", 
        "&-+F6-/]", 
        "tYo7rU{", 
        "Ex\u001f4pEF>e", 
        "6kJOQB\\b", 
        "zQYPrX", 
        "=(2y|8", 
        "ug'iDI}", 
        "Kp:;G3", 
        "(4-ZVZ", 
        ")[hV[2", 
        "}|&06-@", 
        "6Q/@,L", 
        "{}-i9\\", 
        "z'n][g&", 
        "#l_w33+", 
        "~r`8F<", 
        "P ILv{$ B", 
        "[_K2$W!F", 
        "V>@]ch", 
        "dLD^?_", 
        "?LQwx*{O", 
        "94&Kgl3", 
        "!1E%?\u001fQ", 
        ".!`E(5", 
        "j ;xHc", 
        "(QDQ\u001fu", 
        "C{l1`i", 
        "f]JOnF/", 
        "Q\u001f57{V", 
        "Iy$l-U", 
        "\"H?4N\\", 
        "og(#m/", 
        "Mi_^E]E", 
        "Dq[0\u001fY1\u001fD", 
        "L=^@7y5", 
        "7J6v{l", 
        "thwV@a", 
        ">wCSHKW", 
        "WO(*2*", 
        "A<ECv6T", 
        "DF]k\"g", 
        "6CU}6[", 
        "8y1g~L", 
        "\"ysJ{wC", 
        ".Jn4}*Fma", 
        "4s0OosW", 
        "laxPG.", 
        "b?$JzZg", 
        "4hIM4>F", 
        "C/y~ms$", 
        "DNb]EZ", 
        "KKD:u<3E", 
        "FvGGUrZo", 
        "Wy4<zj", 
        "&^w}`[", 
        ":\u001ftG)/", 
        "$<rn9u", 
        "k{&7.{", 
        "9X/30A", 
        "X;KFg!=", 
        "u@/?-i", 
        "0)1>1@J", 
        ".\"Lj|0#", 
        "5I]\\0z", 
        "0q<i? {a", 
        "%rDzMO", 
        "H7@[)z", 
        "Mn;BD ", 
        "wjWd)l|", 
        "X`:x|6", 
        "eDQ16U", 
        "HWfJm-", 
        "7|@Ovc", 
        "fJdL-L", 
        "4l]jGX", 
        "??6Z9\"n", 
        "!U9S'd", 
        "WX}+Z}", 
        ",Aho#v?FV", 
        "]!K=sE", 
        "UUwZUu_V/Ic", 
        "%9#jZ4", 
        ",bKp |=", 
        "q&W6!}qe3~", 
        "sgj'vh", 
        "kiIjapN", 
        "\"|PBnY", 
        "M4rn*O", 
        ":\u001f\"[<T", 
        ">I)fhz<C", 
        "HhPT*p", 
        "I#\\=`;_", 
        "/UF>eTD", 
        "~{5~#r", 
        "!]fyNy", 
        "ukdV6?)", 
        "zJ>nFM", 
        "F'/\"lo", 
        "*<VW<}x\"Dy", 
        ";+bz)Fj&/", 
        "R4:!\"U", 
        "\"Pwc7q", 
        "1b$(a3=", 
        ";s;3On", 
        "=?oKC)=", 
        "Gc5|mus", 
        "jEWWqX", 
        "=,;Q76{", 
        "d`P!nN", 
        "aNxa@`H", 
        "FtR EG", 
        "# `x4:", 
        "{'i1TGq", 
        "mv6TDT", 
        "dist/scripts/lib/jquery-1.11.0.min.jsUT", 
        ">No+Ub=", 
        "y4 $`?", 
        "!*\",+;", 
        "HGNLH=", 
        "Ugv8tf", 
        " $to{|", 
        "/4+Cv1", 
        "H.)b,+", 
        "_849oc", 
        "2}eAX}L", 
        "XE7@`Qt", 
        "7^D5FQ", 
        ";Q]YDyh4*", 
        "O%*J[J", 
        "s8/0:/Z", 
        "jXNuY7", 
        "qKV;p]", 
        "2GE-sU", 
        ")q@Icu", 
        "-ma&*Z", 
        "2G[k!#P@", 
        "!2-fUa", 
        "Jj~iG`\"v", 
        ",m3omw", 
        "8qDfl\u001fM", 
        "FExkQ-", 
        ".c)6)O", 
        "gR%}X +g", 
        "hW':IG", 
        "U9;~w$E", 
        "VjRWofK", 
        "a j)#u", 
        "aRs#z<J ", 
        "GStXC%", 
        "[&WN)8", 
        "e9SQ^%o", 
        "RLqz_;", 
        "m$a'p+", 
        "M8`WUZE|/z!P7", 
        "K|IGu-I", 
        "CEdzl5/ .", 
        "0UvjB;yf>", 
        ")B*V,BM3", 
        "UAM|*Wg", 
        "J*-`^a$4", 
        "q#@4Q<", 
        "%.L>=#1C", 
        "JDDTK0", 
        ")L\\gEa", 
        ";q8J:I|", 
        "4}^Ewe", 
        "dist/scripts/lib/highlight.min.jsUT", 
        "\u001f&>ngAz", 
        "pq:,\u001f|", 
        "7Q0q^<", 
        "<oH24A'", 
        "|`gN:'", 
        "y3kN:[}es", 
        "Tm*,Rt&E", 
        "*?g<qhE", 
        "RD-pO(,,l", 
        ",$}G^1", 
        "S,ngjX", 
        "DuGFr*", 
        "2\"KE(mB", 
        "BAY#;!", 
        "wsv=Q!", 
        "&cc^w[", 
        "*1cUtB-", 
        "$Zp5,LNF*", 
        "MuxY\\U", 
        ">?4pR?", 
        " #<GOH", 
        "|C']sz", 
        "xw=GE\"", 
        "iZ`N=E", 
        "G1Ot\u001fA$t", 
        "&)^q[-RB", 
        "P.r4(M", 
        "v$H%l\\i", 
        "3N:KPm7y.#M", 
        "O&\"BNx", 
        "lldhxI", 
        "Vfe-K6", 
        "%J{%TF", 
        "L2Q6-s ", 
        ")o5[$W", 
        "ydZ\")Y", 
        "X}hcxbY", 
        "&?\\.Ha\u001f", 
        "uLFq$d", 
        ")HZ#4QD", 
        "`S+ml$", 
        "\".o[B6", 
        "uz41_<", 
        "PJPZ!f", 
        "Kwfg,T", 
        "h&(Y/t", 
        "#k~m+\\}tv", 
        "BrxgeG}Z", 
        "lAXQSHV", 
        "k7?kO!", 
        "6v*9?GI4", 
        "h2RXa,", 
        "jK-9}JA", 
        "W4>\\C`y", 
        "; x?eQT", 
        "hx~OIQ", 
        "*fMi\")", 
        ".9M=]D", 
        "i8{m\u001f>3", 
        "neq[`w", 
        "MD\\ohC%8\\{", 
        "]Az?^z", 
        "A:]?\\x", 
        "?vC|y_", 
        "G_?/7'", 
        "2QiQMY", 
        "h\u001f}[,L", 
        "cWNeGA", 
        "'zLlu0h!", 
        ":TQm-*", 
        "+wF$l ", 
        "+Zzr(O!", 
        "1<dk8,", 
        "Iaba%X", 
        "uMWrbd", 
        "V9[s?q\u001f", 
        "{#=_?_6", 
        "mB|r\u001f(@.Dc", 
        "UTiQVI", 
        "gF-+..Z", 
        "G?16ntd", 
        "I~sc]/TV", 
        "D:qg,K", 
        "D9PtO(", 
        "NP?6Z1h", 
        "2d)?_=;", 
        "I4h*te", 
        "eZ>mmc", 
        "`09m%y", 
        "=1;?O>=", 
        "l%R\u001fh,3", 
        "meU\\O:", 
        "&TlRF1", 
        "u6>+L;n", 
        ")roM3q", 
        "d0.j:sA/?", 
        "MbxGv+L<FaE", 
        "=noYiy", 
        ";=>_\\EE", 
        "]6N|]?B|", 
        "8kGO]H", 
        "\u001f#(t0a.", 
        "LIa^k<tn", 
        "&:::!:", 
        "b-oWon", 
        " LO/H9", 
        "4-;]_}", 
        "H7WtuohP", 
        "\\?`fUlT", 
        "~HAKul", 
        "KvMl\\u", 
        "zvWInH", 
        "F]Xq?}{\\~n", 
        "?*#)klc", 
        "J)7&R=", 
        "w~i~iq", 
        "B!)qu}G?", 
        "'#E?&A_V", 
        "t:#GH&", 
        "GKEJ/:*9", 
        "yvvvQvQnf.xfc", 
        "VXTX2mP[~", 
        "BhKlLt", 
        "uEAx dM", 
        "6toh#qQ", 
        "TdGGLg", 
        ":<nh$l", 
        "hf.(PY\u001f", 
        "di]ue0", 
        "qjEhS+", 
        "R_`.wT", 
        "\"$j|D/T", 
        "$QGkw7", 
        "4v7!aE", 
        "P?D2g|{f", 
        "Wg*bx4>", 
        "}CD.qx", 
        "E{#a[$", 
        "&YccC.", 
        "1'fr)X", 
        "aKMFIB ", 
        "m,*,-]", 
        "lAtygy", 
        "{o)%/M", 
        "BAp)q4H", 
        "d;8-?O?", 
        "gmCJ0t", 
        "BX3Ns9", 
        "#6n,[A'1@mV", 
        "(uAx0\"Q", 
        "ae)U3iT", 
        "N8CJe-", 
        "w[JMvw$d", 
        "jhZEky", 
        "QO}'Hw", 
        "\"X~zp7b", 
        "}j_f=+", 
        "LG2WVJ", 
        "z(W9u*T32t", 
        "2QzboCi#", 
        "$/o)3y", 
        "$*(9;\u001f", 
        "2a iyA", 
        "Zlj\u001f55:m\u001fhoXM1", 
        "^KS{SSC;", 
        "KqEq9Q", 
        "R(45o1", 
        "4~$JQ\"", 
        "|\\hKCS'", 
        "voRTBbQ", 
        "x*X+m{", 
        "~uiLl57", 
        "K#]YoF", 
        "r0Ff>w", 
        ">xd}gn", 
        "hH\"Y=\\", 
        ":'|)Yl&", 
        "Hm2^T%", 
        "V`*@B>Q", 
        "o.;<T4E#", 
        "/EZ3Nu01", 
        "l},k/v", 
        "m.G&3tx", 
        "P~c]|s_", 
        "G;.~Oxp", 
        ")^bS95R#2\u001f", 
        "!nlF$fEs`", 
        " 'Z. k", 
        "p=2ifT7`", 
        "Kd\"!U#", 
        ",)@IYar", 
        "tz59HI", 
        "Ve{p`J", 
        "$`f\"1(AJF", 
        "3)K*, 7", 
        "NWG*+J", 
        "ec'oK}?", 
        "p4Q69m", 
        "2,W=AK", 
        "g43s+*,", 
        "D6;EVb(*5", 
        "%S/HHI", 
        "*GjFN^", 
        "Q3RO8{", 
        "NU+5JU", 
        "3-1kebBltj", 
        "[8t$[>.", 
        "NS\\ZLT", 
        "a%-@3*", 
        "Dsj|VB|", 
        "&1>2SV", 
        "KWCY1y", 
        "&;Q1>%", 
        "HIdTdjdN", 
        "3>l<k|", 
        "uVtVwn", 
        "gmW`hy", 
        ":q\"NB&", 
        "}(\u001fWa?", 
        "I$Ih!Z", 
        "Kg*pYP/", 
        "R`5m{4", 
        "oJ/\"+Y", 
        "TwQgW*k", 
        ">3${R${", 
        "vM3qR3", 
        "tn3B7BI", 
        "R0AG0(", 
        "/~4|;[", 
        "JGsttK", 
        "#Rr-hX|", 
        "H,^5X7", 
        "<E!/dr", 
        "]pJP?6", 
        "R<\\\u001fZX/", 
        "*\"@=JQ", 
        "DbHSxM", 
        "Y$lu4D", 
        "=h (k@", 
        "~)~U~uo6/", 
        "~ior/p/", 
        "X]:yf^$", 
        "|aT)}k", 
        "F2,WOL", 
        "^!AD.j", 
        "|1l{}~", 
        "~9ThBy", 
        "b'7&/z", 
        "yx~VzZ", 
        "]nFsZ:=", 
        "\u001fH~eDz1", 
        "Gb/Oz$+q", 
        "%Z;e$[", 
        "zU9Rlr", 
        "P\"\"G4!", 
        "x/IzCF", 
        "9z:nhI", 
        "\"ZZ-GX", 
        "cxfIuZ", 
        ",SRIYq", 
        "Xo0g9\\", 
        "gEta5e", 
        "yyyeye", 
        "E-a3[8", 
        "Ip%y2Z", 
        "\u001fOH|a|", 
        "]i{HM,", 
        "moE Ln+", 
        "Gu.Q&)", 
        "Q>MG7Q", 
        "-+D-'TUu", 
        "S@{Hf&", 
        "+\"W5Mc", 
        "oxuOUO", 
        "}EKsy:", 
        "xSs3M.'", 
        "jN@Fu@I", 
        "C)O2/4", 
        ".EIut[/", 
        "&gfvh5@", 
        "]j8#_f", 
        "A!anFw", 
        "d\u001f8ute", 
        "^_W-EN\\9?87", 
        "5UEo7#", 
        "bdpA(R", 
        "1>'7X~#", 
        "cqfD_:", 
        "MI\"7qN\"7", 
        "@rIIIEIy", 
        "1G$O]m8", 
        "4.xY3z", 
        "L.*O*7", 
        "X_qrGv/U", 
        ":\\^B\\/X", 
        "UWU8\\N/]", 
        "@yljff", 
        "Ft{?S)", 
        "h|kQkKSc", 
        "CD.X.\\", 
        "20?\"&Yi>", 
        "\u001fQjM@Zt", 
        "p*i*g+Q", 
        "J]+pUQ", 
        "2Jc$^k", 
        "3-((3n", 
        "bccc{c[4", 
        "C7mBpv1[", 
        "1{xGXM", 
        "MN5zvA.", 
        "l'=?9Fd", 
        "{MNh4;B", 
        "p\\tjFB0#QK$", 
        ":|buqA", 
        "rUK*)x$", 
        "lV{ptjz", 
        "o,ekvG", 
        "R4APNS", 
        "]!xI@R", 
        "mFSwUG_S", 
        "~doGHes", 
        "7+CvC4", 
        "xDHv,g", 
        "<M&;OS", 
        "^MUp)k", 
        "vmH^vh", 
        "?[^A[P", 
        "Sus5,?", 
        "g6,/3S", 
        ")C<rjk.", 
        "\\~2W]D", 
        "5tjjn9T?", 
        "6`Yai ", 
        "4F^2>x", 
        "DOa+;A", 
        ",@v'4N", 
        "{=RlRRv", 
        "-'5Mjg", 
        "*?7phg", 
        "q`C\\hzI", 
        "$dp(XV", 
        "v*o-}r", 
        "nS)_]t", 
        "}&\u001f$1W", 
        "^m*=DG%", 
        "A1v\\>v", 
        "I4D<D9", 
        "!s],D\"", 
        "]^hW2&", 
        "+Bv\u001fYl#", 
        "a4&NF81", 
        "J\u001f_uwUuuu", 
        ")SwmmYYP", 
        "gJ&J:'", 
        "vDENY|Y", 
        "lMm~I_", 
        "[^O}i!I", 
        "AqCx8B", 
        "Tfv.aj", 
        "BU2^Uj", 
        "rEfzzY", 
        "(X#|4vm", 
        "G)i)81", 
        "5DSP-}O", 
        "M, %X<", 
        "L3wEGc", 
        "xrm6'v", 
        "N}f\\Lb8", 
        ">G(!.:", 
        ",<2<9<;<?|O", 
        "\u001fS\u001fJ}&", 
        "Td&fff", 
        "\"gQyQ]", 
        "mun=xu", 
        "+{GzFW", 
        "Q9UP%UQ5", 
        "`'?+4V", 
        "$wmw'J__S:", 
        "n\"tId\"", 
        "Pf**VT", 
        "uBt:Vf", 
        "29%K;|+|", 
        "zv%=[9", 
        "PR$Oz-`&m", 
        "c64Z?_", 
        "Pez[2|M", 
        "&R$Byj", 
        ">3~;~-", 
        ":dl\"2_", 
        "X41`\\#n]", 
        "suHi&o63p", 
        "QUNMM]", 
        ",/ATBU^7U3", 
        "Uxj|8R", 
        "I%mk6u", 
        "dA?w>`A", 
        "LMh\\%et", 
        "SI:Z.Z", 
        "p&J+I.;", 
        "YD].}D\u001f", 
        "\u001fVoF`4", 
        "FaW61j@@*Xt", 
        "p]k86zf", 
        "dMKdMX", 
        "b@LA88fA", 
        "5\u001fVp`,_", 
        "B|Bvi#", 
        "'d7#X*G", 
        "E^`djg", 
        "~Gt9jK", 
        "4Cn`SBgB", 
        "96kB|\\", 
        "#7,}iI", 
        "`&a}KX", 
        "f8`)K,", 
        "]=q@mjS", 
        "66ahuo9", 
        "#oS}d7", 
        "3)huIL", 
        "rm/*c&", 
        "_BBqZV", 
        "r}8|$m", 
        "hJvfT{", 
        "g@i]SS", 
        "|'4QYb", 
        "g`Uh;{[Du", 
        "KofZJ|,", 
        "YSb:N\\", 
        "h/v*]N", 
        ".}W0=a=", 
        "y9ut96", 
        "mTkcC\"", 
        "Z[N\\7s~", 
        "kr.lVrC", 
        ". =;.hx?.FC", 
        "v\u001f<5C)", 
        "|i9hqm", 
        "*|\\>TJjz(8", 
        "Urw#u\u001f", 
        "SzFU\u001f!}", 
        "\":?V:?v]", 
        "3KKj/TH", 
        "i$5FCQS", 
        "HnHIN?", 
        "rk^}sj", 
        "V6Afv2", 
        "EWEt$:", 
        "H'Fc,C", 
        "0c!.Xy", 
        ":,/Qf*Y", 
        "\"%Kpiq", 
        "IM3W6B", 
        "QNm*jFJZK", 
        "[>3k3yz", 
        "Q_>6:9", 
        "#{DG<&", 
        "R'T[O.", 
        "BZk[!&", 
        "VoLA$W", 
        "x'\\2KA", 
        "suZg[Q", 
        "fXm8YC", 
        "N%Dtq.u", 
        "@{S l3", 
        "}oF#[NB", 
        "e9&'H%", 
        "o(g}ks", 
        "G<Nf(G", 
        "M=unxm", 
        "X[[[_[ogG<", 
        "eaT{{~", 
        "YQ2Q]Ba", 
        "O}3<`E", 
        "JrKbo}=", 
        ",kHjIV", 
        "^V[)li", 
        ">_KuUr", 
        "t.Y^{XQy", 
        "p|9CnW", 
        "]m=;[f", 
        "D}|Om9", 
        "Z9,_?\\", 
        "_DY|';", 
        "8EC{73P", 
        "N#((G+", 
        "HKe\"h\"*", 
        "j0Fn(l", 
        "*P@O#t", 
        "0IfsyZ", 
        "j.C4:'{Hy", 
        "f#{\u001fVc", 
        "F?o@z}Z", 
        "0}LoG[S6", 
        "ie>Y6h", 
        "H(h]IF", 
        "HP_rNE", 
        "tA?\\/Rp>", 
        "GLC6''", 
        "uNS}`\\", 
        "'|{Nw,", 
        "S[yd1Z", 
        "R*E6#p_DS", 
        "|l/\"{Oy", 
        ",|h&Z*Hca", 
        "{[y ^g-", 
        ",_Abfm", 
        "9%%%3%#>1", 
        "!i>V )\u001f", 
        "HRrL99", 
        "0TyK#w9", 
        "&6\\UL-", 
        "$2YLRr", 
        "jNKK+Ns", 
        "HM4h51", 
        "zC|zu#", 
        "qXUM%UY", 
        "iz=hRb", 
        "K^@_B_", 
        "9r$|Fp", 
        "kvkNh^", 
        "X{lYlmlK", 
        "<=ynrg", 
        "d|\"-)-/", 
        "_q-p-u", 
        "[Fn9uk", 
        "jXOUqX", 
        "#kz{LuC", 
        "DITDM4DKt$", 
        "!^RBJI", 
        "MzH/YJ", 
        "9I~I^!", 
        "?[9M=,&W", 
        "qLS@NSBNSDN", 
        "zre_=i", 
        " 1wX/:N", 
        "p BxZ7", 
        "A#R~H<", 
        "how#nm", 
        "S_[C8d", 
        "Mgl[[F", 
        "Jjz @;HY", 
        "r{i\u001fTG", 
        "9PtG=Rl[A", 
        "w(#wm9D", 
        "0c@<jb", 
        "M\"Z:]q", 
        "1q0ftKG", 
        "cVL3Wt.i", 
        "K4&KeZs", 
        "${U*5]j", 
        "rw-,\"+", 
        "vo,nj^b", 
        "2j9B;[6", 
        "Ne^Q3/", 
        "e==]1/ ", 
        ";8Z7&_z", 
        ":,k0~tj", 
        "6v@_W=x`+", 
        "0gqMS:", 
        "OON7-%", 
        "*}UYY#", 
        "pidz0&M", 
        "v%&(Uc", 
        "i)$[x:", 
        "7/3y2jj", 
        "2p:Db:", 
        "qeyt4cUC", 
        "qv@L*Sbh", 
        "nCtkLO", 
        "fCtTBb\\", 
        "jGFZ~pdN^NF", 
        "]7:%hO", 
        "Vp.3G]s", 
        "BoAVFb|\\", 
        "GLDN~mN]\\", 
        "cDQajb", 
        "R-8^MLF", 
        "W(ena/", 
        "i,*;g&", 
        "d}[]6Z", 
        "({!XB[W@", 
        "y_C,\u001fC\u001f,%", 
        "MqV~~N", 
        "I>0en+", 
        "[_?\\lQ", 
        "h5<`M ", 
        "@!ct7?>", 
        ":bL^d)", 
        "[??eODl", 
        "doN[+y", 
        "M=0.<5", 
        ".AjTByr", 
        "i%g8&j#", 
        "MMMM=M", 
        "\\Y%%CV", 
        "5:;4O_", 
        "OBMx9O", 
        "e\"K<2rS", 
        "P@r9IYV", 
        "Y@F~nz", 
        "%W0IpG", 
        "ZuATF/(", 
        "li>Yzu", 
        "GZb#`-w", 
        "]\\^mq$7[", 
        "D<fM8b", 
        "<:<P$0;c", 
        "-6k*hh", 
        "MgqX]I", 
        "1xjdjY", 
        "W:3i&\"/", 
        "e?p`RI", 
        "8?\\c1*", 
        "Y.~-Ne", 
        "D-\"4Y&", 
        "1W%jC'", 
        "#jB\"Nn", 
        "G_QYQW", 
        "7E%Hw(Q", 
        "YRkskE", 
        "lRIYGId", 
        "yzr[Go", 
        ":j2G2G<", 
        "TTNR7K", 
        "r+.IhAc", 
        "F.C&'S5", 
        ">s}e`\"", 
        ", C/QR", 
        "=mFsy$", 
        "2uoEiR ", 
        "HS@L7G]87eN", 
        "+:[U|$KI", 
        "`|e*K-~", 
        ".;897}r", 
        "Fv0@J h", 
        "HRip;R", 
        " B?\"q#!", 
        "gBZExU", 
        "B$'&Tn", 
        "ZHuS9x;", 
        "Ds@hn!4G", 
        "M=m3A\\$", 
        "Q~OL%74", 
        "SGuU9kW", 
        "*G-Vvc", 
        "</_D$Hb\u001f*", 
        "_']I~wQ", 
        "Gl%k;\"f ", 
        "Rr4SB/", 
        "TOw{[K", 
        "rZ;Vn061", 
        "l~S{pP", 
        "~q~wPr", 
        "_JPO~<", 
        "\u001f\"_-wo", 
        "O>Mp]f", 
        "\\\"(*\"\"UT", 
        "T-)6j2", 
        "qlYzeS", 
        "[6p/l)v", 
        ":`;f)b", 
        "hZ>>2H", 
        "B'ecbR", 
        ">GW;+q", 
        "uUVRWx", 
        "tq*Oh~", 
        "A9W\"=/|", 
        "%7#+#>", 
        "F?[FjB", 
        "ly]8J^", 
        "Ec<#/:s51", 
        "k]%SB^OVn4M", 
        "r,mKm>", 
        "Fry67q", 
        "A;-ACAA", 
        "\\B`eBBj", 
        "J>Z?x=", 
        "O9,?,g", 
        "~5@8<!", 
        "sA!B^!", 
        "yjyJxj|", 
        "M%!#>#N#c#", 
        "NF!E6E", 
        "|I]MnM", 
        "UDUAUs", 
        "Rtpo4n", 
        "N1bfNSS", 
        "I;JKe\u001f", 
        "8I=\"f]", 
        "DY EYdEY", 
        "^A_I_Q_", 
        "Be&PBq", 
        "\\9=xjwc", 
        "JT-rM*RYP", 
        "K)cxSAZc", 
        "+-fmbv", 
        "dist/assets/fonts/Open_Sans/OpenSans-Italic.ttfUT", 
        "i.\\gAka", 
        "Xdkrc]P6", 
        "36{LVf", 
        ":$fptTd", 
        "ZubgReiSb", 
        "vR#;qv", 
        "MMIZuRSAS", 
        "b0o=);", 
        "S9fB^'", 
        "\"Xyj'\"\"", 
        "I.^?$a", 
        ").6.!nG", 
        "x))$ixRmRcRk", 
        "5=&=1=?", 
        "g}4F4F7", 
        "'|>Q>1ib", 
        "jkk/,W,\u001f", 
        "_V2+U+", 
        "8l[+5q", 
        "9dN-v't", 
        "Ekx-?Dje", 
        "Ao5:R?<", 
        "mt~s3W", 
        "s>X|V&", 
        "Y1,C8N[c", 
        "lN9TCv", 
        "~iT6|v", 
        "T&'+|N", 
        "M(=:m23q", 
        " |1{,|", 
        ">l[5cGT`V", 
        "O_x}#g", 
        "<Pb5H2", 
        "8#&#!umA", 
        "R&u/OI", 
        "fLtHv_V", 
        "ike%\u001fm", 
        "tN7xZyBH$", 
        "x2.$1m;", 
        "\u001f~9\\v9", 
        "82+,!8@", 
        "6=1&fb", 
        "<kaEfvE", 
        "]:08b-", 
        "ILumoC`", 
        "HM3di,", 
        ">8:qNldnr", 
        "aTL;_o", 
        "9ZcmH+", 
        ":OUsFG", 
        "7Tr!D$s", 
        "TR3#B45233M", 
        "D\u001f+\u001f~f|", 
        "#uEp`ug", 
        "sWy<w4", 
        "%b$tK$2N", 
        "$e10.-)Y^=", 
        "/Kg?7G", 
        "u#):7%", 
        "$a\\aL#", 
        "GM1`G&M", 
        "rs?SxDDx", 
        "g[\u001f?<r", 
        "x}sdBm", 
        "pyRrDdz", 
        ">E^&g$", 
        "$'WDrri", 
        "6yIi~.", 
        "aMkF&&'", 
        "jDRa?j", 
        "5VZ\\+*i", 
        "}z$wB?", 
        "&~?/r*", 
        "zo6Wj?", 
        "hU^Axf", 
        "YK^y.o", 
        "DEb-^J", 
        "PZ$:j\\", 
        "'q;!v%", 
        "sNgm-8", 
        "6<5 9c", 
        "\u001f<bhX:wi", 
        "dl)!8s+:f", 
        "vX><'nE", 
        "0-5.+?", 
        "w1HK9#", 
        "U?<bTh`", 
        ";[w*/I-7w", 
        "P\"XZS6", 
        "P/P<s&< ", 
        "AT4CL(^Q", 
        "('3g8d", 
        "LH%<B&", 
        "{o@,Rl", 
        "%G'[C?r", 
        "REDJ)*\"nT", 
        "\\WHHhExnD~n", 
        "Feog%%8|", 
        "B-!$!J", 
        ">1+d=HBA", 
        "DOVv@b", 
        "I^-44<8:", 
        ";KOI|,)K", 
        "A>e,N/", 
        ";}'Y(b", 
        "oM(Q3k", 
        "4-+<.7D4I~HHVxfF", 
        "pgzVVr", 
        "rfZ(`_", 
        "#A}uVo", 
        "u(xcVz", 
        "iqJ2i=", 
        "rH+8Cu", 
        "|vT|tB", 
        "uC1&zE", 
        ";2998J", 
        "T%O*xPP", 
        "T;.xqkm", 
        "g$1Oz)", 
        "4p/MXt;x", 
        ",L>N/i9", 
        "FY5u{1", 
        "w,9Kh%", 
        "9Q+J(2", 
        "gDx1>P", 
        "*NO]919", 
        "=<)<)eDvnG", 
        "5G9e\":", 
        "irXKP>", 
        "ZId ^;S", 
        "*{KP^_G", 
        "Mj`uuN", 
        "ch$!IM]", 
        "&\u001fN1}19", 
        "xDutr5", 
        "9aL\u001f\"N+", 
        "pZ'[/}", 
        "w<(6cc", 
        "rR^sMx", 
        "]M0IpPL_", 
        "_!`Z!c", 
        "}na*SqS", 
        ">2]!,[%", 
        "t;=w6s", 
        "v4.)8J", 
        "#!s[Tm", 
        "qpizn<", 
        "]7j^tj", 
        "`&cU|%Q/ ", 
        ">u,L)N)", 
        "\\o{fkg", 
        "8ts)In", 
        "5(0y$Q", 
        "`_EJvX", 
        "KwXm`-", 
        "\u001fP>+$vlz", 
        "/W:(\"3'", 
        "'o>y7E>", 
        "lom#*`om", 
        "yV\"}m0", 
        "{iI>/C", 
        "S1yr-'x", 
        ">oYz;<HZJr\u001f", 
        "lFAg<N", 
        "p0D-JZ", 
        "QF\\U@n", 
        " G>5)Q", 
        "(ZL,!bz", 
        ">B-ezJ", 
        "?'$/(u", 
        "Dj/6^\u001f", 
        "CEd!m,", 
        "1-98^z", 
        ",oN:HYB..", 
        "!8#H'X#h#x", 
        "Y#OA2)", 
        "z[~Q8Y", 
        "_nQLiS1w", 
        "SF#e3[", 
        ".Y%/9m", 
        "$5_~}m", 
        "&<~&4)", 
        "WE.t+Vf", 
        "1n0nPC!", 
        "aqkp~E", 
        "].+Cf_", 
        "~R\\}6?", 
        "lIHWi(|", 
        "aP/Q8_", 
        "4]TQRr", 
        "_m-tt*", 
        "Aj'zrb#A", 
        "`Q4*AYC", 
        "C%domo~ig9", 
        "^*[~@PX2a", 
        "\\WmG^kyg", 
        "]M}7N?", 
        "]DM,\\I", 
        ")H}}H!", 
        "NBhhC=", 
        "B\u001f:v/UI Q", 
        "E-#XqV", 
        "-eK<hVB5", 
        "{l7xkf", 
        "G\u001f<Hm:x", 
        "Wc3S,4", 
        "Ffp0nW", 
        "%5}ueg", 
        "*|,Xq!]A", 
        "q\"~4\"~L", 
        "2enS1x+Z", 
        "s]Zk,N", 
        "\u001fGFG>l", 
        "c\\DkzE", 
        " pTSp'", 
        "NDZ4dZi", 
        "\\wFn^ow.^_", 
        "pNF`-F", 
        "kGs`{0", 
        "-|nn]y", 
        " Q.'x%x", 
        "/f\"v1?", 
        "2Vl!;DS", 
        "f,n=&Ga", 
        "?(`Esf", 
        "'J0j-9", 
        "D@/\"\"r", 
        "dphYmJUP", 
        "Gu9Y\u001foP", 
        "j?\"4z ;", 
        "\"09pKAG", 
        "pdgk:vL", 
        "@HLNKMK", 
        "l;&Q0V", 
        "#Uu\\ ##", 
        "AW5d>8|", 
        "WVZu0+", 
        "&0_TAtHv", 
        "@QVvvn", 
        ";uTeTc", 
        "W~aa=$M", 
        "/|BjEA", 
        "{o6sF-", 
        "L&IGFT", 
        "\"kn 8nr", 
        "N`ks2,", 
        "9^Mu1'", 
        "H5AM[=", 
        "uul|k1W", 
        "~(CG`Y", 
        "6AHIMi", 
        "!ZL6S}", 
        "YWFFzf&", 
        "'<dPL{xm", 
        "-%=:u.", 
        "\"TP5Xx", 
        "G>*R3*E", 
        ",\"\"\"\"*2", 
        "(E`'wk<", 
        "uoTbL`v", 
        "mQG&,v", 
        "P^^uaE[", 
        "e97&^!", 
        "BOSwk;", 
        "TrXJup", 
        "5vn;\"qdkY", 
        "[x6P'V", 
        "*4+'aO^s", 
        ",Pe9DYj5c", 
        "t^[CU]g", 
        "WUQ~gp", 
        "X:=Nu\\", 
        "[dZ%C/", 
        "7ZnR<p", 
        "EC\"@R5i", 
        "c[7g<cCv", 
        "u`)%>u", 
        "yjU.0P", 
        "C[}}rD", 
        "*?za[5", 
        "\\XOg-'", 
        "L2veah{", 
        ";~KSwr", 
        "Xfrv 88}-", 
        "B^U{1a", 
        "aLi`vJ", 
        "C[@Z@Y", 
        ".~znw,wsJ%\u001f", 
        " XWP^_m8", 
        "vA6NM%", 
        "9nY^35", 
        "Az\u001fEDD", 
        "QZFQP)", 
        "]@6}<1", 
        "9)>3):sRd", 
        "7_51r>h", 
        "_'%noU", 
        "_U&^zf:", 
        "igkdAu2", 
        ":{oPzn", 
        ".jMXf,>", 
        "8ml,kQ", 
        "a+amlA", 
        "5Xm3gs[Y'", 
        "[\\G2?KG", 
        "x,wjxE6LJq", 
        ":21iN\\flA", 
        "#o3g?tF,", 
        "I\".CkJH", 
        "~\\eReRX", 
        "Fq[SO9", 
        "Q2-H/F?", 
        "jK14?<", 
        "|n\u001fdzd\"", 
        "O^9R9-p", 
        "b(BZ`vu", 
        "=^W@96", 
        "?}UmWw", 
        "a7H%*z", 
        "#gNdv.2", 
        ",5t4ut", 
        "o;]To}(y", 
        "?M@L8h", 
        "6 .<q\u001f", 
        "F=\u001f_\u001fh4", 
        "Jr\u001f}j\u001f", 
        ";)\u001fUa\"#*-", 
        "Z#2Lc1", 
        "#GFIir&+", 
        "C*VhDJ", 
        "^36E.H", 
        "P?]?_?[", 
        "mvQ9NF", 
        "uV?,@x", 
        "WW]WWM", 
        "K'0sK=", 
        "`4^t@;2", 
        ")aIr-u", 
        "ujKW>F", 
        "Z!Yu6S", 
        "Px9)>*", 
        "8XoUhU", 
        "@dpFuw", 
        "!=E22spd}", 
        "V1u|vc", 
        "NsbH}Q", 
        "A3I=}Y", 
        "_^<zq%", 
        "0H:H}!E@J", 
        "@oL@FV", 
        "_p`pTpvpy", 
        "}Rz''%", 
        "Hy*)Ou", 
        "-(4AUl", 
        "J*HyNI)", 
        "o.3O7\u001f", 
        "1-b~D]DsDK", 
        "B&V-a{", 
        "qKnQQAAQQ.>", 
        ">[OG1Tk+.", 
        "b\u001f4yPF", 
        "#\"d]V&", 
        "6mZ6eAB", 
        "Y4#bTJ", 
        "G,V(%4", 
        "T>GT>CT>", 
        ",\"$b0#", 
        "1D6y.{", 
        "i|MJZ/", 
        ">;gCeU", 
        "(qWe.lK", 
        "S!l|nT", 
        "dh!=DS!B", 
        "^>>%u{", 
        "\u001f]e~]^", 
        ":91eDbA", 
        "XH.IBHB", 
        "q%aao`]%X", 
        "1&hlJV", 
        "$S OT1", 
        "9A=8Ara?", 
        "79O0_~b", 
        "Ao6'1Zc", 
        "\\;ofKu", 
        "Ljvg'y", 
        "~|bW:]", 
        "#TcU/s", 
        "EQga[gi", 
        "_71Op2", 
        "py'w{S", 
        "[h%caE", 
        "Dp\u001fX1hU", 
        "N~+)Gk", 
        "SA/:YYk55", 
        "fSSm*Z", 
        "n~j^`(nD", 
        "[(b.-Y,", 
        "bt/lvw", 
        "x4kl*L", 
        "d2=|-<", 
        ">0n\\p=", 
        "f/DoKz&", 
        "G1/R2)>", 
        "v{`i(y=", 
        "]\u001f({sG", 
        "]Na`U{", 
        "k#(#F>", 
        "F#*X5Kobi0", 
        "T*5dMx", 
        "/DGk(i", 
        "y976I{", 
        "BkeE))", 
        "z2jls~", 
        "so\"Hh2dnn", 
        "4+%%B~", 
        "d~{aYuY", 
        "ZPVU6U)", 
        "sDO\"%zh", 
        ")m7n!}", 
        "-PBAGY", 
        "iSdvb|h", 
        "L&gsdx-", 
        "%K^x|L\"", 
        "ev;lnA", 
        "<O>2B`", 
        "^5Xa7Xap", 
        "N05Kai", 
        "\u001fu,mzX[O", 
        "l6C%tM;1V", 
        "%-BIy2B", 
        "ZD!tv-", 
        "c_'.5oM?", 
        "I|c_BU&=A;", 
        "PLm\"80", 
        "7u#VCk>", 
        "9eImXSkV&\\z", 
        "F(-~J>F", 
        "x]Rf;tV", 
        "(x3WiR^}]", 
        "p&f9!T", 
        "25c59)", 
        "NjNlEd4\\n", 
        "kPB^V@", 
        "ToLT$r", 
        "_h*3G^", 
        "cc+i\"i", 
        "z<dYE0E<E=E8E9E*", 
        "+*t3r2n", 
        "L6 EYdB", 
        "*c'=aPI", 
        "\\[FYTu", 
        "z_vYJ[", 
        "'y1OIj", 
        " sh1R'", 
        "{;+m>Q>T", 
        "H*yR(f", 
        "Llvn?8oj", 
        "p'.x4mF.R", 
        "*pHS\\PyT", 
        "SnG,D*", 
        "TOj,;Z", 
        "5co\"=M", 
        "rxto=:+", 
        "oZ]y;S_", 
        "Ut;}Vw.G", 
        "n?q3n6X", 
        ": j{e<I", 
        "?<Zwf4", 
        "K]2LqA", 
        "y.yL_-r", 
        "\"+9]x\"", 
        "1(AvAK", 
        "ml'L4I", 
        "G19^Aj", 
        "FR,><@[", 
        "w\u001fDX8rC", 
        "rt4F=H", 
        "6!(Hjn", 
        "#fB!4#C", 
        "SSkD<;", 
        "|]9p39V", 
        "Ok)fE3", 
        "qZ?D<PGS", 
        "-V*m<R;w", 
        "^.3?<$O", 
        "YlHl9nY", 
        "6]V>#~f?", 
        "ICGQo!<", 
        "3Jg\"Rq", 
        "tYB[iF", 
        "D5T`+MS", 
        "ct%9|>", 
        "cVmYk:", 
        "JCA;&f", 
        "R?Voy &", 
        "([v|fQ", 
        "cI\">]b`", 
        "b*+ki/", 
        "Y{h^P6i)", 
        "jJ&'h|RO", 
        ")PVkVK", 
        ";R]i9>", 
        "+R6R#{g", 
        "w?.[eo", 
        "k=YoZo", 
        "NN,LL Ln", 
        "eVr$AO", 
        "\u001fs,*&J", 
        "2mD'LA>", 
        "CtFObX8", 
        "K-inpU", 
        "Yq1F cQYC", 
        ";jU>|YyOL", 
        "N=9mKwu?", 
        "bqkQx1n", 
        "lO{0cM#fgp4", 
        "TT^T]TWTdb", 
        "S>jSimA]", 
        "q8!fvU0g", 
        "1XQJ'\u001f#", 
        "9y.m% ", 
        "6>Xy`i", 
        "R\\R?'p", 
        "eQh:\"&G", 
        "WL# 'Rw", 
        "I4np N", 
        "an;'Eq", 
        "5T@*1E", 
        "GU$6l-", 
        "hL+5XFk", 
        "fhFBt=", 
        "H~ehbp", 
        "Px9U4I", 
        "KkzKuEuEh}", 
        ";j1Z;/H", 
        "g<F~am", 
        "Dv3@w@", 
        "!@@D\"\"", 
        "{klB#}", 
        "nEr{+@", 
        "HtQ7|[", 
        "Tv?Vqy", 
        "366-11", 
        "xGDL7eL", 
        "BP)sP)f", 
        "O\"Pe\u001fp", 
        "gRINwKD", 
        "C4/v__", 
        "a|=<[g", 
        "!g7:UEE", 
        " Hp22O", 
        "/H-4Q]", 
        "t4+^)^", 
        "wuYvjB", 
        "D*)vK}!", 
        "/GO|B\";", 
        "{E-ZqxR", 
        "|$N^lSl", 
        ">~ZenN/", 
        "$c0[~5", 
        "?];.ef", 
        "%*6Ugq", 
        "_U^IU&", 
        "c|t;.o", 
        ".uc:)S@`", 
        "1ysGlJ", 
        ",#a|t`", 
        "|dt\\^|Ql^7V", 
        "\"<Wm?s", 
        "#}DO'5", 
        "#cWVSj", 
        "kUlrv\\", 
        "Ukbm-}", 
        "n02\"<\"", 
        "@?Hd%$x", 
        "BHR`5A", 
        "d)qs&61J", 
        "xxx@zv", 
        ";QGp\"z", 
        "]14u\\NY", 
        "4oB:ix", 
        "#6\":jx", 
        "k^>05D", 
        "/=pC je", 
        "\\vuZp[X{", 
        "[~u0.'[", 
        "=8]Q\"JR", 
        "ZLL\\Tj", 
        "8D'[**", 
        "vShF<\"e/", 
        "]#Xd^Z", 
        "J3}u>\\>'M", 
        "{fsZs&", 
        ">^n!gr", 
        "7kIf)TE", 
        "bug5W,3", 
        "u=YV3K", 
        "C'mZO)Z", 
        "]h!G< 7", 
        "r=lWk`", 
        ".>fy}B", 
        "Co7z*9PN", 
        "X|j]Po", 
        "uw+bAR", 
        "\u001fI6.Y@N", 
        "b@uW3SZ", 
        "#YXHGWI", 
        "wR'nEAv", 
        "EjxSJ&O", 
        "fjR<\\B", 
        "} zKu+JNjR3D=", 
        "\\Dk#2#", 
        "r_0\"Jw(T", 
        "}KW4d)", 
        "j@o!lA\\~]", 
        "6y-+[E", 
        "v_/$$8C", 
        "h\"3#&z", 
        "{Xpwn/.-b", 
        "8TUbK8", 
        "pf:il0", 
        "G{(941", 
        "X?n#v8\u001f", 
        "79$y#Y", 
        "V]`BE`B", 
        ")'P)+p\"#", 
        "*#0!-`+-", 
        ")-P)% ?H", 
        "yNDsNDdN", 
        "QzY^y~", 
        "ZE~3`U", 
        "DEU$-$", 
        "=ZCYCXC+", 
        ">|{m+_", 
        ":n.UK/", 
        "P-M[-MC-MY-mO", 
        "n[t@!Q.s", 
        "'(wlm{&", 
        "zyDSkA*", 
        "M})LNx", 
        "AOR..F", 
        "bc#.h>", 
        ".,&AqJ", 
        "bu;m91", 
        "MPm*\u001f)", 
        "?l^.QZ", 
        "PD*:%)", 
        "GX6z9Xm~", 
        "4jID)b", 
        "GcF?p[1", 
        "M44_a!", 
        "EVOqL%pw", 
        "R9ga]nt", 
        "P!i#7m", 
        "e|RlRn", 
        "'B?a}B", 
        ">Pi#~`", 
        "=r!yK/", 
        "x%H9Ek", 
        "'Gq.TBIXn", 
        "sZ.dqH4", 
        "r@'M&im", 
        "dl!K-1gyuTX", 
        "k{KdQg", 
        "?/a(Q0", 
        "CK:}9`V{", 
        "EN)V|;", 
        "Px8_9<", 
        "B<?`$A", 
        "Lyu1j3", 
        "o/Xxo/", 
        ">>$,rl", 
        "E~~/_HS!", 
        "Vi3J=~h", 
        "~ ik-f(", 
        "(s#1uL", 
        "Gbolmp^W", 
        "'uI =>", 
        "G15Cp_", 
        "xTu 45", 
        "435*cE~", 
        "eI<SDu[", 
        "+;mbP[", 
        ">.yKy8", 
        "-2(+u&", 
        "#V2C),", 
        "tb{gH\u001fl", 
        "U\\]6L/\u001f", 
        "7_^tWR", 
        "scripts/", 
        "manifest.json", 
        "prcA&7d", 
        "[MX)](5g", 
        "_locales/", 
        "assets/", 
        "images/logo16.png", 
        "dIDATx", 
        "a~wcv!R", 
        "IXp% 1p", 
        "#oZxsz\\", 
        "images/logo128-grey.png", 
        ".xCY\"]H", 
        "Ljjj>N", 
        "jQl 78$d", 
        "P=*Q+_", 
        "Q5_C97", 
        "images/logo16-grey.png", 
        "lNsiHZJ", 
        "?39+kk", 
        "\u001f#S{M]", 
        "'43Ire", 
        "images/logo128.png", 
        "P\\lEYt", 
        "%5=@;F(;C-/", 
        "+JyE^xS", 
        "!/RU+S", 
        "#bq\\2N}F", 
        "s#?PH(Z", 
        "/LG2J[E", 
        "0|?U9kez", 
        "lg:!9T7.19I", 
        ":B9(W40 ", 
        "N|w'VpX", 
        "images/logo64.pngeWy8", 
        "DsS=z:.:", 
        "$88X:X^", 
        "dBj+4H", 
        "<.W0Dnd", 
        "wn?]*I", 
        "&ieV9U", 
        "images/ChromeWebStore.png", 
        "~j.9uww", 
        "P?5434A", 
        "x>8@l{G", 
        ":\u001f!r,,`", 
        "o3)j,!h", 
        "ISq&EF", 
        "K^K#B~2E", 
        "9U@,uJ", 
        "TQ7S!4L", 
        "Q\"4W!Th", 
        "Z#?p4w", 
        "n8UYvP", 
        "rnSybN", 
        "01Kk|!", 
        "`<p1s]", 
        "Rh@Hvzz", 
        "w+9L%8", 
        "r-q?9ry", 
        "Z9\\=0g", 
        "qkPaN7'", 
        "KfQ1(X", 
        "Og#c5X", 
        "<#r945N", 
        "RK8':M", 
        "(~{'z&", 
        "~xU%nA", 
        "images/logo64-grey.pngeW", 
        "m-gO0|", 
        "\"Mjx%K", 
        "qmHqqi", 
        " L+s:`", 
        "style/content.css", 
        "GfFFdFfF", 
        "C !1([9$2", 
        "%>JplX", 
        "RH`Dpp", 
        ". $7\",", 
        "e^}_de", 
        "etyxp53", 
        "$M4:?:", 
        "!D)GdH#8t0)", 
        "}!D)Gd", 
        "=RmQ@{$;", 
        "OIT\u001f#|", 
        "oL2p*z", 
        "&FG\u001fgxF", 
        "t24\u001fI[", 
        "oju>+0U", 
        "'\u001fFsei", 
        "Gflu2&", 
        "Cr@14=*&I", 
        "scripts/run.jsS*-NU(.)", 
        "scripts/module/", 
        "scripts/lib/", 
        "scripts/model.js", 
        "scripts/app.js", 
        "?KmJ1B", 
        "&n<4x<", 
        "_locales/zh/", 
        "_locales/en/", 
        "assets/fonts/", 
        "scripts/module/reader/", 
        "scripts/module/background/", 
        "scripts/module/update/", 
        "scripts/module/content/", 
        "scripts/module/version.js", 
        "8-Ty[{", 
        "scripts/module/fonts.js}R", 
        "K*qABB\\8", 
        "M'HlRF", 
        "586 <j", 
        "scripts/module/common/", 
        "scripts/lib/polyfill.min.js", 
        "w${f$;e$_", 
        "l{_vOWM7", 
        "<g=3GJ", 
        "do-j!N", 
        "Ku R7\"RW/", 
        "9`K\\f!", 
        "}2k6'NB", 
        "!{63n:)", 
        "u@/?-i", 
        "0)1>1@J", 
        ".\"Lj|0#", 
        "5I]\\0z", 
        "0q<i? {a", 
        "%rDzMO", 
        "H7@[)z", 
        "Mn;BD ", 
        "wjWd)l|", 
        "X`:x|6", 
        "eDQ16U", 
        "HWfJm-", 
        "7|@Ovc", 
        "fJdL-L", 
        "4l]jGX", 
        "??6Z9\"n", 
        "!U9S'd", 
        "WX}+Z}", 
        ",Aho#v?FV", 
        "]!K=sE", 
        "UUwZUu_V/Ic", 
        "%9#jZ4", 
        ",bKp |=", 
        "q&W6!}qe3~", 
        "sgj'vh", 
        "kiIjapN", 
        "\"|PBnY", 
        "M4rn*O", 
        ":\u001f\"[<T", 
        ">I)fhz<C", 
        "HhPT*p", 
        "I#\\=`;_", 
        "/UF>eTD", 
        "~{5~#r", 
        "!]fyNy", 
        "ukdV6?)", 
        "zJ>nFM", 
        "F'/\"lo", 
        "*<VW<}x\"Dy", 
        ";+bz)Fj&/", 
        "R4:!\"U", 
        "\"Pwc7q", 
        "1b$(a3=", 
        ";s;3On", 
        "=?oKC)=", 
        "Gc5|mus", 
        "jEWWqX", 
        "=,;Q76{", 
        "d`P!nN", 
        "aNxa@`H", 
        "FtR EG", 
        "# `x4:", 
        "{'i1TGq", 
        "mv6TDT", 
        "scripts/lib/jquery-1.11.0.min.js", 
        ">No+Ub=", 
        "y4 $`?", 
        "!*\",+;", 
        "HGNLH=", 
        "Ugv8tf", 
        " $to{|", 
        "/4+Cv1", 
        "H.)b,+", 
        "_849oc", 
        "2}eAX}L", 
        "XE7@`Qt", 
        "7^D5FQ", 
        ";Q]YDyh4*", 
        "O%*J[J", 
        "s8/0:/Z", 
        "jXNuY7", 
        "qKV;p]", 
        "2GE-sU", 
        ")q@Icu", 
        "-ma&*Z", 
        "2G[k!#P@", 
        "!2-fUa", 
        "Jj~iG`\"v", 
        ",m3omw", 
        "8qDfl\u001fM", 
        "FExkQ-", 
        ".c)6)O", 
        "gR%}X +g", 
        "hW':IG", 
        "U9;~w$E", 
        "VjRWofK", 
        "a j)#u", 
        "aRs#z<J ", 
        "GStXC%", 
        "[&WN)8", 
        "e9SQ^%o", 
        "RLqz_;", 
        "m$a'p+", 
        "M8`WUZE|/z!P7", 
        "K|IGu-I", 
        "CEdzl5/ .", 
        "0UvjB;yf>", 
        ")B*V,BM3", 
        "UAM|*Wg", 
        "J*-`^a$4", 
        "q#@4Q<", 
        "%.L>=#1C", 
        "JDDTK0", 
        ")L\\gEa", 
        ";q8J:I|", 
        "4}^Ewe", 
        "scripts/lib/highlight.min.js", 
        "\u001f&>ngAz", 
        "pq:,\u001f|", 
        "7Q0q^<", 
        "<oH24A'", 
        "|`gN:'", 
        "y3kN:[}es", 
        "Tm*,Rt&E", 
        "*?g<qhE", 
        "RD-pO(,,l", 
        ",$}G^1", 
        "S,ngjX", 
        "DuGFr*", 
        "2\"KE(mB", 
        "BAY#;!", 
        "wsv=Q!", 
        "&cc^w[", 
        "*1cUtB-", 
        "$Zp5,LNF*", 
        "MuxY\\U", 
        ">?4pR?", 
        " #<GOH", 
        "|C']sz", 
        "xw=GE\"", 
        "iZ`N=E", 
        "G1Ot\u001fA$t", 
        "&)^q[-RB", 
        "P.r4(M", 
        "v$H%l\\i", 
        "3N:KPm7y.#M", 
        "O&\"BNx", 
        "lldhxI", 
        "H2f2gB2f", 
        "Xp :fh", 
        "^TTUlL", 
        "bTLj^E", 
        ")]a^'&045", 
        "_locales/zh/messages.json", 
        "_locales/en/messages.json", 
        "assets/fonts/Merriweather/", 
        "assets/fonts/Open_Sans/", 
        "scripts/module/reader/event.jse", 
        "scripts/module/reader/module.js", 
        "Uv6e{k/", 
        "Ej<I|Wu", 
        "_,p<(8", 
        "rz2ih]", 
        "~ww~ag", 
        "9T-@S_", 
        "j{%$;rN", 
        "B3@q`bW", 
        "scripts/module/reader/view.js", 
        ":\\%^-09\\0P,", 
        "TI&!TJ", 
        "scripts/module/background/module.js", 
        "\\o~KU'", 
        "ELu<Ya", 
        "xqEk>[", 
        "BcjDxJk", 
        "-;W$RqX", 
        "zFHlcy:", 
        "khYO(*@|+", 
        "scripts/module/update/module.jsM", 
        "scripts/module/update/view.jsm", 
        "scripts/module/content/event.js", 
        "r:$ZkPC", 
        "scripts/module/content/module.js", 
        "z!dHJ=1", 
        " o6U^V", 
        "*]=6KIhg", 
        "|+ 8oe", 
        "{ ^,Q7", 
        "scripts/module/content/view.js", 
        "QPj/^e", 
        "u7GT`P", 
        "#USW8a^", 
        "e;[SF+(", 
        "JHwIHwR", 
        "oo>@5(", 
        "5{!;@T.", 
        "scripts/module/common/module.js", 
        "3rz8gI>g?", 
        "&wZcQ!", 
        "yq#=\\ &", 
        "QUd3DkWM", 
        ".YGde$", 
        "8`s${,", 
        "assets/fonts/Merriweather/Merriweather-Bold.ttf", 
        "VqwYkK", 
        "C6!nC|", 
        "p(O\\j}", 
        "nBj-\\wIj", 
        "R[%o;\\", 
        "rH*YPV7", 
        "Lg]n]e", 
        "lgA/b7J*", 
        "%Vq(IJ", 
        "=noYiy", 
        ";=>_\\EE", 
        "]6N|]?B|", 
        "8kGO]H", 
        "\u001f#(t0a.", 
        "LIa^k<tn", 
        "&:::!:", 
        "b-oWon", 
        " LO/H9", 
        "4-;]_}", 
        "H7WtuohP", 
        "\\?`fUlT", 
        "~HAKul", 
        "KvMl\\u", 
        "zvWInH", 
        "F]Xq?}{\\~n", 
        "?*#)klc", 
        "J)7&R=", 
        "w~i~iq", 
        "B!)qu}G?", 
        "'#E?&A_V", 
        "t:#GH&", 
        "GKEJ/:*9", 
        "yvvvQvQnf.xfc", 
        "VXTX2mP[~", 
        "BhKlLt", 
        "uEAx dM", 
        "6toh#qQ", 
        "TdGGLg", 
        ":<nh$l", 
        "hf.(PY\u001f", 
        "di]ue0", 
        "qjEhS+", 
        "R_`.wT", 
        "\"$j|D/T", 
        "$QGkw7", 
        "4v7!aE", 
        "P?D2g|{f", 
        "Wg*bx4>", 
        "}CD.qx", 
        "E{#a[$", 
        "&YccC.", 
        "1'fr)X", 
        "aKMFIB ", 
        "m,*,-]", 
        "lAtygy", 
        "{o)%/M", 
        "BAp)q4H", 
        "d;8-?O?", 
        "gmCJ0t", 
        "BX3Ns9", 
        "#6n,[A'1@mV", 
        "(uAx0\"Q", 
        "ae)U3iT", 
        "N8CJe-", 
        "w[JMvw$d", 
        "jhZEky", 
        "QO}'Hw", 
        "\"X~zp7b", 
        "}j_f=+", 
        "LG2WVJ", 
        "z(W9u*T32t", 
        "2QzboCi#", 
        "$/o)3y", 
        "$*(9;\u001f", 
        "2a iyA", 
        "Zlj\u001f55:m\u001fhoXM1", 
        "^KS{SSC;", 
        "KqEq9Q", 
        "R(45o1", 
        "4~$JQ\"", 
        "|\\hKCS'", 
        "voRTBbQ", 
        "x*X+m{", 
        "~uiLl57", 
        "K#]YoF", 
        "r0Ff>w", 
        ">xd}gn", 
        "hH\"Y=\\", 
        ":'|)Yl&", 
        "Hm2^T%", 
        "V`*@B>Q", 
        "o.;<T4E#", 
        "/EZ3Nu01", 
        "l},k/v", 
        "m.G&3tx", 
        "P~c]|s_", 
        "G;.~Oxp", 
        ")^bS95R#2\u001f", 
        "!nlF$fEs`", 
        " 'Z. k", 
        "p=2ifT7`", 
        "Kd\"!U#", 
        ",)@IYar", 
        "tz59HI", 
        "Ve{p`J", 
        "$`f\"1(AJF", 
        "3)K*, 7", 
        "NWG*+J", 
        "ec'oK}?", 
        "p4Q69m", 
        "2,W=AK", 
        "g43s+*,", 
        "D6;EVb(*5", 
        "%S/HHI", 
        "*GjFN^", 
        "Q3RO8{", 
        "NU+5JU", 
        "3-1kebBltj", 
        "[8t$[>.", 
        "NS\\ZLT", 
        "a%-@3*", 
        "Dsj|VB|", 
        "&1>2SV", 
        "KWCY1y", 
        "&;Q1>%", 
        "HIdTdjdN", 
        "3>l<k|", 
        "uVtVwn", 
        "gmW`hy", 
        ":q\"NB&", 
        "}(\u001fWa?", 
        "I$Ih!Z", 
        "\"ZLKh)", 
        "K6]h9b", 
        "s`xUo`xH^/J.", 
        "z#mfsW", 
        "\"\u001fN./'\u001fo'", 
        "NIh<BiN", 
        "ECkYJ1", 
        "]JhKhy", 
        "N\u001f,fPqk", 
        "lke(mU", 
        "E0D(![o", 
        "--f}bv", 
        "*L_2Z9", 
        "Q<zePr", 
        "assets/fonts/Merriweather/Merriweather-Regular.ttf"
    ], 
    "metadata": {
        "output": {
            "pcap": {
                "basename": "dump.pcap", 
                "sha256": "704e5e5b3234433c01fcfd1b20a306e77e985038120492dc53965c3edd38a4ea", 
                "dirname": ""
            }
        }
    }
}